llm_council.py
llm_council-0.1.3.dist-info/LICENSE
llm_council-0.1.3.dist-info/METADATA
llm_council-0.1.3.dist-info/WHEEL
llm_council-0.1.3.dist-info/entry_points.txt
llm_council-0.1.3.dist-info/top_level.txt
llm_council-0.1.3.dist-info/RECORD
