Metadata-Version: 2.2
Name: llm-council
Version: 0.1.3
Summary: Use LLM to generate and execute commands in your shell
Author: Simon Willison
License: MIT
Project-URL: homepage, https://github.com/nuwandavek/llm-council
License-File: LICENSE
Requires-Dist: llm
Requires-Dist: prompt_toolkit>=3.0.43
Requires-Dist: llm-claude-3
Requires-Dist: llm-gemini
